Workbook

Sheet novos_usuarios_ult-7-meses
A1: ANO-MÊS | B1: QUANTIDADE NOVOS USUARIOS
A2: 2025-08 | B2: 101126
A3: 2025-09 | B3: 96091
A4: 2025-10 | B4: 93911
A5: 2025-11 | B5: 114136
A6: 2025-12 | B6: 109961
A7: 2026-01 | B7: 108147
A8: 2026-02 | B8: 78419
A9: média | B9: =AVERAGE(B2:B8) -> 100255.86

Sheet planos-assinados-ult-7-meses
A1: ANO-MÊS | B1: TIPO DE PLANO | C1: QTD NOVOS ASSINANTES | D1: Assinatura R$ | E1: Tx Churn % | F1: LTV Bruto R$
A2: 2025-08 | B2: plano familia | C2: 5406 | D2: 121 | E2: 0.07 | F2: =C2*D2/E2 -> 9344657.1
A3: 2025-08 | B3: plano HBO | C3: 137 | D3: 40 | E3: 0.08 | F3: =C3*D3/E3 -> 68500
A4: 2025-08 | B4: plano premiere | C4: 725 | D4: 90 | E4: 0.09 | F4: =C4*D4/E4 -> 725000
A5: 2025-08 | B5: plano TELECINE | C5: 95 | D5: 40 | E5: 0.075 | F5: =C5*D5/E5 -> 50666.667
A6: 2025-08 | B6: compras / alugueis | C6: 5000 | D6: 25 | F6: =C6*D6 -> 125000
A7: 2025-09 | B7: plano familia | C7: 4672 | D7: 121 | E7: 0.07 | F7: =C7*D7/E7 -> 8075885.7
A8: 2025-09 | B8: plano HBO | C8: 126 | D8: 40 | E8: 0.08 | F8: =C8*D8/E8 -> 63000
A9: 2025-09 | B9: plano premiere | C9: 607 | D9: 90 | E9: 0.09 | F9: =C9*D9/E9 -> 607000
A10: 2025-09 | B10: plano TELECINE | C10: 71 | D10: 40 | E10: 0.075 | F10: =C10*D10/E10 -> 37866.667
A11: 2025-09 | B11: compras / alugueis | C11: 5000 | D11: 25 | F11: =C11*D11 -> 125000
A12: 2025-10 | B12: plano familia | C12: 4218 | D12: 121 | E12: 0.07 | F12: =C12*D12/E12 -> 7291114.3
A13: 2025-10 | B13: plano HBO | C13: 65 | D13: 40 | E13: 0.08 | F13: =C13*D13/E13 -> 32500
A14: 2025-10 | B14: plano premiere | C14: 698 | D14: 90 | E14: 0.09 | F14: =C14*D14/E14 -> 698000
A15: 2025-10 | B15: plano TELECINE | C15: 90 | D15: 40 | E15: 0.075 | F15: =C15*D15/E15 -> 48000
A16: 2025-10 | B16: compras / alugueis | C16: 5000 | D16: 25 | F16: =C16*D16 -> 125000
A17: 2025-11 | B17: plano familia | C17: 8337 | D17: 121 | E17: 0.07 | F17: =C17*D17/E17 -> 14411100
A18: 2025-11 | B18: plano HBO | C18: 81 | D18: 40 | E18: 0.08 | F18: =C18*D18/E18 -> 40500
A19: 2025-11 | B19: plano premiere | C19: 850 | D19: 90 | E19: 0.09 | F19: =C19*D19/E19 -> 850000
A20: 2025-11 | B20: plano TELECINE | C20: 111 | D20: 40 | E20: 0.075 | F20: =C20*D20/E20 -> 59200
A21: 2025-11 | B21: compras / alugueis | C21: 5000 | D21: 25 | F21: =C21*D21 -> 125000
A22: 2025-12 | B22: plano familia | C22: 10869 | D22: 121 | E22: 0.07 | F22: =C22*D22/E22 -> 18787843
A23: 2025-12 | B23: plano HBO | C23: 70 | D23: 40 | E23: 0.08 | F23: =C23*D23/E23 -> 35000
A24: 2025-12 | B24: plano premiere | C24: 355 | D24: 90 | E24: 0.09 | F24: =C24*D24/E24 -> 355000
A25: 2025-12 | B25: plano TELECINE | C25: 93 | D25: 40 | E25: 0.075 | F25: =C25*D25/E25 -> 49600
A26: 2025-12 | B26: compras / alugueis | C26: 5000 | D26: 25 | F26: =C26*D26 -> 125000
A27: 2026-01 | B27: plano familia | C27: 12051 | D27: 121 | E27: 0.07 | F27: =C27*D27/E27 -> 20831014
A28: 2026-01 | B28: plano HBO | C28: 92 | D28: 40 | E28: 0.08 | F28: =C28*D28/E28 -> 46000
A29: 2026-01 | B29: plano premiere | C29: 1013 | D29: 90 | E29: 0.09 | F29: =C29*D29/E29 -> 1013000
A30: 2026-01 | B30: plano TELECINE | C30: 87 | D30: 40 | E30: 0.075 | F30: =C30*D30/E30 -> 46400
A31: 2026-01 | B31: compras / alugueis | C31: 5000 | D31: 25 | F31: =C31*D31 -> 125000
A32: 2026-02 | B32: plano familia | C32: 11140 | D32: 121 | E32: 0.07 | F32: =C32*D32/E32 -> 19256286
A33: 2026-02 | B33: plano HBO | C33: 73 | D33: 40 | E33: 0.08 | F33: =C33*D33/E33 -> 36500
A34: 2026-02 | B34: plano premiere | C34: 776 | D34: 90 | E34: 0.09 | F34: =C34*D34/E34 -> 776000
A35: 2026-02 | B35: plano TELECINE | C35: 73 | D35: 40 | E35: 0.075 | F35: =C35*D35/E35 -> 38933.333
A36: 2026-02 | B36: compras / alugueis | C36: 5000 | D36: 25 | F36: =C36*D36 -> 125000

Sheet assinantes-ativos-mensais
A1: MAU Médio último 12 M | B1: 850000 | D1: ANO-MÊS | E1: TIPO PLANO | F1: TOTAL ASSINANTES | G1: VALOR: ASSINATURA/ALUGUEL | H1: RECEITA : ASSINATURA + ALUGUEL
A2: Percentual assinantes ativos | B2: 0.17 | D2: 46023 | E2: Plano Familia | F2: =B3*B5 -> 122825 | G2: 121 | H2: =F2*G2 -> 14861825
A3: Assinantes ativos por mês | B3: =B1*B2 -> 144500 | D3: 46023 | E3: Plano HBO | F3: =B3*B6 -> 11560 | G3: 40 | H3: =F3*G3 -> 462400
A4: % de assinantes por plano | B4: 1 | D4: 46023 | E4: Plano Premiere | F4: =B3*B7 -> 5780 | G4: 90 | H4: =F4*G4 -> 520200
A5: Plano Familia | B5: 0.85 | D5: 46023 | E5: Plano TELECINE | F5: =B3*B8 -> 4335 | G5: 40 | H5: =F5*G5 -> 173400
A6: Plano HBO | B6: 0.08 | D6: 46023 | E6: compras/alugueis | F6: 5000 | G6: 25 | H6: =F6*G6 -> 125000
A7: Plano Premiere | B7: 0.04 | D7: 46054 | E7: Plano Familia | F7: 122825 | G7: 121 | H7: =F7*G7 -> 14861825
A8: Plano TELECINE | B8: 0.03 | D8: 46054 | E8: Plano HBO | F8: 11560 | G8: 40 | H8: =F8*G8 -> 462400
A9: Compras + Alugueis | B9: =F6/B3 -> 0.034602076 | D9: 46054 | E9: Plano Premiere | F9: 5780 | G9: 90 | H9: =F9*G9 -> 520200
D10: 46054 | E10: Plano TELECINE | F10: 4335 | G10: 40 | H10: =F10*G10 -> 173400
D11: 46054 | E11: compras/alugueis | F11: 5000 | G11: 25 | H11: =F11*G11 -> 125000
D12: 46082 | E12: Plano Familia | F12: 122825 | G12: 121 | H12: =F12*G12 -> 14861825
D13: 46082 | E13: Plano HBO | F13: 11560 | G13: 40 | H13: =F13*G13 -> 462400
D14: 46082 | E14: Plano Premiere | F14: 5780 | G14: 90 | H14: =F14*G14 -> 520200
D15: 46082 | E15: Plano TELECINE | F15: 4335 | G15: 40 | H15: =F15*G15 -> 173400
D16: 46082 | E16: compras/alugueis | F16: 5000 | G16: 25 | H16: =F16*G16 -> 125000
D17: 46113 | E17: Plano Familia | F17: 122825 | G17: 121 | H17: =F17*G17 -> 14861825
D18: 46113 | E18: Plano HBO | F18: 11560 | G18: 40 | H18: =F18*G18 -> 462400
D19: 46113 | E19: Plano Premiere | F19: 5780 | G19: 90 | H19: =F19*G19 -> 520200
D20: 46113 | E20: Plano TELECINE | F20: 4335 | G20: 40 | H20: =F20*G20 -> 173400
D21: 46113 | E21: compras/alugueis | F21: 5000 | G21: 25 | H21: =F21*G21 -> 125000
... D61: 46357 | E61: compras/alugueis | F61: 5000 | G61: 25 | H61: =F61*G61 -> 125000
D62: Receita Total Anual | H62: =SUM(H2:H61) -> 193713900

Sheet TOFU + BOFU Metrics
A1: MAU Médio último 12 M | B1: Aquisição usuarios por mês | C1: Aquisição Organica | D1: Aquisição Paga | E1: Conversão Compra/Aluguel | F1: Conversão Assinatura | G1: Taxa Ativação -> Conversão
A2: 850000 | B2: 70000 | C2: 0.75 | D2: 0.25 | E2: =B2*0.03 -> 2100 | F2: 15000 | G2: =F2/B2 -> 0.21428571
A4: Tipo de Usuário | B4: ICP (resumo comportamental) | C4: CAC Google Ads | D4: CAC Meta Ads | E4: CAC TikTok Ads | F4: Valor Assinatura / Aluguel | G4: Tx Churn / mês | H4: LTV Bruto (R$) | I4: LTV/CAC (Google) | J4: LTV/CAC (Meta) | K4: LTV/CAC (TikTok)
A5: Plano Família | B5: família, bundle seeker, alto valor percebido | C5: 90 | D5: 120 | E5: 140 | F5: 121 | G5: 0.08 | H5: =F5/G5 -> 1512.5 | I5: =H5/C5 -> 16.805556 | J5: =H5/D5 -> 12.604167 | K5: =H5/E5 -> 10.803571
A6: Plano Premiere | B6: fã de futebol, alta urgência (jogo ao vivo) | C6: 60 | D6: 90 | E6: 110 | F6: 90 | G6: 0.12 | H6: =F6/G6 -> 750 | I6: =H6/C6 -> 12.5 | J6: =H6/D6 -> 8.3333333 | K6: =H6/E6 -> 6.8181818
A7: Plano HBO | B7: cinéfilo/series, baixa urgência | C7: 80 | D7: 110 | E7: 130 | F7: 40 | G7: 0.1 | H7: =F7/G7 -> 400 | I7: =H7/C7 -> 5 | J7: =H7/D7 -> 3.6363636 | K7: =H7/E7 -> 3.0769231
A8: Plano Telecine | B8: consumidor ocasional de filmes | C8: 75 | D8: 100 | E8: 120 | F8: 40 | G8: 0.09 | H8: =F8/G8 -> 444.44444 | I8: =H8/C8 -> 5.9259259 | J8: =H8/D8 -> 4.4444444 | K8: =H8/E8 -> 3.7037037
A9: Compras + Aluguéis | B9: consumo impulsivo (TVOD) | C9: 25 | D9: 40 | E9: 35 | F9: 25 | G9: =1/7 -> 0.14285714 | H9: =F9/G9 -> 175 | I9: =H9/C9 -> 7 | J9: =H9/D9 -> 4.375 | K9: =H9/E9 -> 5
A11: Tipo de Usuário | B11: Intenção | C11: Melhor Canal | D11: CAC Esperado | E11: Por quê
A12: Plano Família | B12: média | C12: Meta Ads | D12: R$ 70 – 120 | E12: storytelling + remarketing
A13: Plano Premiere | B13: alta | C13: Google Ads | D13: R$ 45 – 80 | E13: demanda direta (jogo)
A14: Plano HBO | B14: média/baixa | C14: Meta Ads | D14: R$ 80 – 130 | E14: descoberta
A15: Plano Telecine | B15: média/baixa | C15: Meta Ads | D15: R$ 75 – 120 | E15: consumo ocasional
A16: Compras + Aluguéis | B16: baixa/impulso | C16: TikTok Ads | D16: R$ 15 – 45 | E16: comportamento impulsivo

Sheet Funnel Analytics
A1: AQUISIÇÃO (Traffic / MAU growth) | B1: ATIVAÇÃO (MAU → Engajamento inicial) | C1: EXPERIÊNCIA DE CONTEÚDO (Engajamento real) | D1: INTENÇÃO DE ALUGUEL/ASSINATURA | E1: CONVERSÃO (Ativação paga) | F1: RETENÇÃO (pós-assinatura)
A2: Objetivo: trazer usuários Etapas: Impressão (Ads / Orgânico) Clique Landing / App install Primeiro acesso (MAU) KPIs: CTR CPI / CAC (aquisição) % novos MAU Drop-offs típicos: criativo ruim → baixo CTR fricção no install/login app pesado / crash | B2: Objetivo: fazer o usuário “ver valor” Etapas: Cadastro/login Primeira navegação Primeiro play (conteúdo iniciado) KPIs: % MAU → play Time to first play sessões por usuário Drop-offs críticos: usuário entra e não dá play catálogo confuso recomendação ruim 👉 esse é um dos MAIORES gargalos normalmente | C2: Objetivo: criar hábito Etapas: 1º conteúdo → 2º conteúdo minutos assistidos frequência semanal KPIs: Watch time conteúdos por sessão D1 / D7 retention Drop-offs: conteúdo não engaja buffering / UX ruim falta de continuidade | D2: Objetivo: levar o usuário até o paywall Etapas: visita página de plano clique em “assinar” seleção de plano KPIs: % MAU → paywall CTR paywall plano mais clicado Drop-offs: preço percebido alto falta de clareza de valor excesso de opções | E2: Objetivo: transformar em assinante Etapas: seleção plano cadastro pagamento aprovação pagamento KPIs: taxa de conversão (você já tem ~19%) falha de pagamento abandono de checkout Drop-offs críticos: fricção no pagamento falta de trial surpresa de preço 👉 esse é o gargalo que você já identificou | F2: Objetivo: manter assinante Etapas: uso contínuo consumo recorrente renovação KPIs: churn (7–12% no seu caso) sessões/mês conteúdo consumido Drop-offs: assinante não usa conteúdo não renova interesse
A3: ROAS REAL = CAC/LTV de 3x a 5x estimado | E3: Drop off ATIVAÇÃO --> CONVERSÃO de 81% | F3: Churn 8% a 12% mensal (dependendo do plano)

Sheet Marketing Budget Optimizer
B2: Scenario | C2: Investimento mensal Marketing (atual) | D2: Aquisição usuarios por mês | E2: Taxa Ativação Assinantes | F2: Assinantes Ativados | G2: Alugadores/Compradores Ativados | H2: Assinantes Plano Familia Ativados | I2: Assinantes Plano Premiere Ativados | J2: Assinantes Plano HBO Ativados | K2: Assinantes Plano Telecine Ativados | L2: Retorno Investimento mensal | M2: Incremento Otimização | N2: ROAS
B3: Atual | C3: =L12 -> 2273684.4 | D3: 25000 | E3: 0.35 | F3: =D3*E3 -> 8750 | G3: =5000*0.25 -> 1250 | H3: =12051*0.62 -> 7471.62 | I3: =1013*0.85 -> 861.05 | J3: =192 -> 192 | K3: 187 | L3: =M12 -> 12325274 | M3: N/A | N3: =L3/C3 -> 5.4208375
B4: Optimized | C4: =L20 -> 2099166.7 | D4: 30000 | E4: 0.45 | F4: =D4*E4 -> 13500 | G4: 550 | H4: =F4*0.75 -> 10125 | I4: =F4*0.25 -> 3375 | J4: 0 | K4: 0 | L4: =M20 -> 17941562 | M4: =(L4-L3)/L3 -> 0.45567252 | N4: =L4/C4 -> 8.5469929
B6: Scenario | C6: Tipo de Usuário | D6: Intenção | E6: Melhor Canal | F6: CAC Aquisição Esperado | G6: CAC Assinante Esperado | H6: Por quê | I6: Valor Assinatura / Aluguel | J6: Tx Churn / mês | K6: LTV Bruto (R$) | L6: Investimento Campanha | M6: Retorno Campanha | N6: ROAS
B7: Atual | C7: Plano Família | D7: média | E7: Meta Ads | F7: 90 | G7: =F7/E3 -> 257.14286 | H7: storytelling + remarketing | I7: 121 | J7: 0.08 | K7: =I7/J7 -> 1512.5 | L7: =G7*H3 -> 1921273.7 | M7: =K7*H3 -> 11300825 | N7: =M7/L7 -> 5.8819444
C8: Plano Premiere | D8: alta | E8: Google Ads | F8: 55 | G8: =F8/E3 -> 157.14286 | H8: demanda direta (jogo) | I8: 90 | J8: 0.12 | K8: =I8/J8 -> 750 | L8: =G8*I3 -> 135307.86 | M8: =K8*I3 -> 645787.5 | N8: =M8/L8 -> 4.7727273
C9: Plano HBO | D9: média/baixa | E9: Meta Ads | F9: 105 | G9: =F9/E3 -> 300 | H9: descoberta | I9: 40 | J9: 0.1 | K9: =I9/J9 -> 400 | L9: =G9*J3 -> 57600 | M9: =K9*J3 -> 76800 | N9: =M9/L9 -> 1.3333333
C10: Plano Telecine | D10: média/baixa | E10: Meta Ads | F10: 98 | G10: =F10/E3 -> 280 | H10: consumo ocasional | I10: 40 | J10: 0.09 | K10: =I10/J10 -> 444.44444 | L10: =G10*K3 -> 52360 | M10: =K10*K3 -> 83111.111 | N10: =M10/L10 -> 1.5873016
C11: Compras + Aluguéis | D11: baixa/impulso | E11: TikTok Ads | F11: 30 | G11: =F11/E3 -> 85.714286 | H11: comportamento impulsivo | I11: 25 | J11: =1/7 -> 0.14285714 | K11: =I11/J11 -> 175 | L11: =G11*G3 -> 107142.86 | M11: =K11*G3 -> 218750 | N11: =M11/L11 -> 2.0416667
K12: Totais | L12: =SUM(L7:L11) -> 2273684.4 | M12: =SUM(M7:M11) -> 12325274 | N12: =M12/L12 -> 5.4208375
B14: Scenario | C14: Tipo de Usuário | D14: Intenção | E14: Melhor Canal | F14: CAC Aquisição Esperado | G14: CAC Assinante Esperado | H14: Por quê | I14: Valor Assinatura / Aluguel | J14: Tx Churn / mês | K14: LTV Bruto (R$) | L14: Investimento Campanha | M14: Retorno Campanha | N14: ROAS
B15: Optimized | C15: Plano Família | D15: média | E15: Meta Ads | F15: 75 | G15: =F15/E4 -> 166.66667 | H15: storytelling + remarketing | I15: 121 | J15: 0.08 | K15: =I15/J15 -> 1512.5 | L15: =G15*H4 -> 1687500 | M15: =K15*H4 -> 15314062 | N15: =M15/L15 -> 9.075
C16: Plano Premiere | D16: alta | E16: Google Ads | F16: 50 | G16: =F16/E4 -> 111.11111 | H16: demanda direta (jogo) | I16: 90 | J16: 0.12 | K16: =I16/J16 -> 750 | L16: =G16*I4 -> 375000 | M16: =K16*I4 -> 2531250 | N16: =M16/L16 -> 6.75
C17: Plano HBO | D17: média/baixa | E17: Meta Ads | F17: 105 | G17: =F17/E4 -> 233.33333 | H17: descoberta | I17: 40 | J17: 0.1 | K17: =I17/J17 -> 400 | L17: =G17*J4 -> 0 | M17: =K17*J4 -> 0 | N17: 0
C18: Plano Telecine | D18: média/baixa | E18: Meta Ads | F18: 98 | G18: =F18/E4 -> 217.77778 | H18: consumo ocasional | I18: 40 | J18: 0.09 | K18: =I18/J18 -> 444.44444 | L18: =G18*K4 -> 0 | M18: =K18*K4 -> 0 | N18: 0
C19: Compras + Aluguéis | D19: baixa/impulso | E19: TikTok Ads | F19: 30 | G19: =F19/E4 -> 66.666667 | H19: comportamento impulsivo | I19: 25 | J19: =1/7 -> 0.14285714 | K19: =I19/J19 -> 175 | L19: =G19*G4 -> 36666.667 | M19: =K19*G4 -> 96250 | N19: =M19/L19 -> 2.625
K20: Totais | L20: =SUM(L15:L19) -> 2099166.7 | M20: =SUM(M15:M19) -> 17941562 | N20: =M20/L20 -> 8.5469929

Sheet PNL Analysis
B2: Platform characteristics | F2: Costs Structure
B3: Average Monthly Active Users | C3: 900000 | F3: Domain | G3: Description | H3: FTEs | I3: Total Cost (month)
B4: Total number of playback per month | C4: 12000000 | E4: 1 | F4: Engineering | G4: Backend + BFF + Frontend squads | H4: 35 | I4: =17000000/12 -> 1416666.7
B5: Total VOD contents on catalog | C5: 50000 | E5: 2 | F5: Cloud & Backend Infra | G5: APIs, ingestion, storage | H5: 3 | I5: =9000000/12 -> 750000
B6: Total LIVE channels on catalog | C6: 220 | E6: 3 | F6: CDN (Largest Cost Driver) | G6: Video delivery (HD streaming) | H6: 3 | I6: =30000000/12 -> 2500000
B7: Video content quality | C7: No 4K (HD/SD only) | E7: 4 | F7: Data & Analytics | G7: Pipelines, tracking, BI | H7: 2 | I7: =2000000/12 -> 166666.67
B8: Number of commercial offers | C8: ~35 subscription plans | E8: 5 | F8: Product | G8: App experience (TV, mobile, web), Features (continue watching, ...), UX/UI (home, navigation) | H8: 6 | I8: 350000
B9: Churn rate (monthly) | C9: 9%–12% | E9: 6 | F9: Marketing/Growth | G9: Paid media (Google, Meta, YouTube), Acquisition (TOFU), Retargeting, CRM (email, push) | H9: 6 | I9: 2000000
B10: Content Distribution Technology | C10: CDN-based delivery | E10: 7 | F10: Content | G10: Suply Side, Licensing (Telecine, Universal+, Premiere), Catalog strategy, Content mix (movies, sports, series) | H10: 8 | I10: 4000000
B11: Assinantes ativos por mês | C11: 145000 | E11: 8 | F11: Admin | G11: HR, IT, FINOPS, etc ... | H11: 8 | I11: 400000
B12: % Assinantes plano familia | C12: 0.85 | F12: Total | H12: =SUM(H4:H11) -> 71 | I12: =SUM(I4:I11) -> 11583333
B13: % Assinantes plano Premiere | C13: 0.08 | F13: Revenue Structure
B14: % Assinantes plano HBO | C14: 0.04 | F14: Domain | G14: Description | I14: Total Revenue (month)
B15: % Assinantes plano Telecine | C15: 0.03 | E15: 1 | F15: Subscription | I15: =SUM(I16:I19) -> 16363250
B16: % Usuarios Compras/Alugueis | C16: 0.01 | E16: 1.1 | F16: Plano Familia | I16: =C11*C12*'Marketing Budget Optimizer'!I7 -> 14913250
E17: 1.2 | F17: Plano Premiere | I17: =C11*C13*'Marketing Budget Optimizer'!I8 -> 1044000
E18: 1.3 | F18: Plano Telecine | I18: =C11*C15*'Marketing Budget Optimizer'!I10 -> 174000
E19: 1.4 | F19: Plano HBO | I19: =C11*C14*'Marketing Budget Optimizer'!I9 -> 232000
E20: 2 | F20: Rentals | I20: =C11*C16*0.8*'Marketing Budget Optimizer'!I11 -> 29000
E21: 3 | F21: Purchases | I21: =C11*C16*0.2*('Marketing Budget Optimizer'!I11+20) -> 13050
F22: Total | I22: =SUM(I15,I20,I21) -> 16405300
